MANIFEST.in
README
setup.cfg
setup.py
robolearnr/__init__.py
robolearnr_python.egg-info/PKG-INFO
robolearnr_python.egg-info/SOURCES.txt
robolearnr_python.egg-info/dependency_links.txt
robolearnr_python.egg-info/not-zip-safe
robolearnr_python.egg-info/top_level.txt