Metadata-Version: 1.1
Name: robolearnr-python
Version: 0.1.4
Summary: SDK for Robolearn
Home-page: https://github.com/NoUseFreak/robolearnr-python
Author: Dries De Peuter
Author-email: dries@nousefreak.be
License: MIT
Platform: UNKNOWN
Classifier: License :: OSI Approved :: MIT License
Classifier: Operating System :: OS Independent
Classifier: Programming Language :: Python
Classifier: Programming Language :: Python :: 2.7
